{"server_type": "forge", "server_version": "1.20.1", "version_jdk": "17", "gbs_de_ram_a_usar": "12", "servicio_a_usar": "playit", "actualizaciones_discord": false, "webhook_de_discord": "", "iniciando_servidor": false, "decir_ip": false, "usar_dropbox": true, "token_dropbox": "\u001b[200~sl.CBW4HNWVoL0NhgnxSaakT5JbnPnH5wDtiffyapX3wahrvSMZqf9U_lbLRrad7pAB-HQ1ls5IHqLlDKFrf8fZ7Czo0hEt0jbUJt8SMlwrU94XtUMjRghKyXjndWsyTuo5jM7rBfdI7w81\u001b[201~", "debug_mode": false, "flags": "-Xms2G -Xmx12G", "usar_lfs": false, "zerotier_network": "", "backup_mode": "luna", "backup_auto": true, "online-mode": true}